_distorm3.cp37-win32.pyd
distorm3/__init__.py
distorm3/__main__.py
distorm3/_generated.py
distorm3/__pycache__/__init__.cpython-37.opt-1.pyc
distorm3/__pycache__/__main__.cpython-37.opt-1.pyc
distorm3/__pycache__/_generated.cpython-37.opt-1.pyc
distorm3-3.5.2.dist-info/COPYING
distorm3-3.5.2.dist-info/METADATA
distorm3-3.5.2.dist-info/WHEEL
distorm3-3.5.2.dist-info/top_level.txt
distorm3-3.5.2.dist-info/RECORD
